java/__init__.py
java/io/File.py
java/io/IOException.py
java/io/PrintStream.py
java/io/__init__.py
java/lang/Exception.py
java/lang/IllegalArgumentException.py
java/lang/IllegalCallerException.py
java/lang/Object.py
java/lang/RuntimeException.py
java/lang/System.py
java/lang/Throwable.py
java/lang/UnsupportedOperationException.py
java/lang/__init__.py
java/nio/__init__.py
java/nio/file/FileSystem.py
java/nio/file/FileSystems.py
java/nio/file/Files.py
java/nio/file/Path.py
java/nio/file/__init__.py
java/python/__init__.py
java/python/lang/ConsoleOutputPrintStream.py
java/python/lang/IllegalInstantiationException.py
java/python/lang/__init__.py
java/util/Properties.py
java/util/__init__.py
VampireAPI-0.3.1.dist-info/METADATA
VampireAPI-0.3.1.dist-info/WHEEL
VampireAPI-0.3.1.dist-info/top_level.txt
VampireAPI-0.3.1.dist-info/RECORD
