Metadata-Version: 2.1
Name: VampireAPI
Version: 0.3.1
Summary: Just Another Vampire Api 4 Python
Home-page: https://github.com/bastie/PythonVampire
Author: Sͬeͥbͭaͭsͤtͬian
Author-email: bastie@users.noreply.github.com
License: UNKNOWN
Platform: UNKNOWN
Classifier: Programming Language :: Python :: 3
Classifier: License :: OSI Approved :: Apache Software License
Classifier: Development Status :: 3 - Alpha
Classifier: Operating System :: OS Independent
Classifier: Intended Audience :: Developers
Classifier: Topic :: Software Development :: Libraries :: Java Libraries
Requires-Python: >=3.6
